AUTHORS
INSTALL
LICENSE
MANIFEST.in
README.rst
setup.py
django_rwiki.egg-info/PKG-INFO
django_rwiki.egg-info/SOURCES.txt
django_rwiki.egg-info/dependency_links.txt
django_rwiki.egg-info/not-zip-safe
django_rwiki.egg-info/requires.txt
django_rwiki.egg-info/top_level.txt
docs/Makefile
docs/source/conf.py
docs/source/index.rst
rwiki/__init__.py
rwiki/admin.py
rwiki/forms.py
rwiki/models.py
rwiki/tests.py
rwiki/urls.py
rwiki/views.py
rwiki/migrations/0001_initial.py
rwiki/migrations/0002_auto__del_field_changes_page.py
rwiki/migrations/0003_auto__add_field_changes_page.py
rwiki/migrations/0004_auto__del_category__chg_field_page_category.py
rwiki/migrations/0005_auto__chg_field_page_category.py
rwiki/migrations/0006_auto__del_changes__del_field_page_category.py
rwiki/migrations/0007_auto__add_field_page_public.py
rwiki/migrations/__init__.py
rwiki/templates/rwiki/default.html
rwiki/templates/rwiki/page_form.html
rwiki/templates/rwiki/wider.html